{
  "exam_code": "104_1_1_1",
  "year": "104",
  "question_count": 80,
  "questions": [
    {
      "id": 1,
      "question": "《神農本草經》將365 種藥物分為三品，其下品藥的主要功能為下列何者？",
      "options": {
        "A": "養命",
        "B": "滋補",
        "C": "養性",
        "D": "治病"
      }
    },
    {
      "id": 2,
      "question": "有關法醫學的敘述，下列何者正確？",
      "options": {
        "A": "中國法醫學起步雖早，但第一本有系統的法醫專書卻晚於西方350 年",
        "B": "外國最早的法醫專書為美國人所著",
        "C": "中國第一本法醫專書為宋慈所著的《洗冤集錄》",
        "D": "元代王與，根據《洗冤集錄》、《結案式》、《無冤錄》三本書，結合個人經驗以及元朝檢驗制 度寫成《平冤錄》一書"
      }
    },
    {
      "id": 3,
      "question": "下列那位醫家提出醫師治病，應當安神定志，無欲無求，先發大慈惻隱之心？",
      "options": {
        "A": "華佗",
        "B": "孫思邈",
        "C": "扁鵲",
        "D": "喻嘉言"
      }
    },
    {
      "id": 4,
      "question": "有關李杲對脾胃生理病理的論述，下列何者錯誤？",
      "options": {
        "A": "造成脾胃疾患的誘因，包含勞倦、憂思與飢飽",
        "B": "脾胃為元氣之本，內傷脾胃，百病由生",
        "C": "內傷熱證，主以甘溫除熱，升舉清陽，潛降陰火",
        "D": "強調脾胃疾病當陰陽雙補，並留意脾胃與心、肝之藏象連結"
      }
    },
    {
      "id": 5,
      "question": "有關「朝代－醫家－著作」的配對，下列何者正確？",
      "options": {
        "A": "南宋－寇宗奭－《本草衍義》",
        "B": "元－王好古－《湯液本草》",
        "C": "元－劉完素－《醫學啟源》",
        "D": "南宋－朱橚－《救荒本草》"
      }
    },
    {
      "id": 6,
      "question": "有關明清婦科名著之略況，下列敘述何者錯誤？",
      "options": {
        "A": "王肯堂編撰之《女科證治準繩》主要是參考了薛己校注陳自明的《婦人大全良方》",
        "B": "《濟陰綱目》為武之望以《女科證治準繩》為基礎，重新分析編次補充之作品",
        "C": "萬全的《萬氏女科》主張調經以理氣補心脾為主",
        "D": "《傅青主女科》之調經用藥主張源自明朝薛己之「乙癸同治」，並提出心肝脾腎同治法"
      }
    },
    {
      "id": 7,
      "question": "明清西方傳教士來中國藉醫療傳教，並未能對當時中西醫學交流產生顯著影響，其原因下列何者最 不貼切？",
      "options": {
        "A": "當時傳入醫學的實際療效，未必比傳統中醫高明",
        "B": "《全體新論》等書並未能達到傳播理論的效果",
        "C": "未能持續得到當時政治權力的支持",
        "D": "傳教時禁止中國籍教徒祭祖，引起不滿"
      }
    },
    {
      "id": 8,
      "question": "明末清初對中醫學文獻的整理與研究特色，下列敘述何者錯誤？",
      "options": {
        "A": "以考據學方法作考證、校訂、注釋、輯復",
        "B": "針對醫籍文字深入考證，但與臨證實務略有距離",
        "C": "採用近代西醫學知識協助注釋古醫籍",
        "D": "文獻編纂有多種體裁，如醫案、醫話、類書、工具書等"
      }
    },
    {
      "id": 9,
      "question": "《素問．生氣通天論篇》述及「陰者，藏精而起亟；陽者，衛外而爲固」，表達了下列何種陰陽的 關係？",
      "options": {
        "A": "陰陽對立",
        "B": "陰陽轉化",
        "C": "陰陽消長",
        "D": "陰陽互用"
      }
    },
    {
      "id": 10,
      "question": "王先生身體發熱已十餘天，咽痛如裂，舌紅起刺，口乾不欲飲，汗雖暢但體表觸之仍熱甚，脈來浮數， 軟大而無力，按之豁然而空，微細欲絕，煩躁面赤，肢冷囊縮，下列有關其病機的論述何者最適宜？",
      "options": {
        "A": "陰盛於下，逼陽於上",
        "B": "陰虛則外熱",
        "C": "陽氣太盛，陰氣不能榮",
        "D": "陽虛則外寒"
      }
    },
    {
      "id": 11,
      "question": "以陰陽說明人體的病理變化，在陰陽偏勝方面，下列敘述何者錯誤？",
      "options": {
        "A": "重陽必陰，陽勝則陰病",
        "B": "溫熱邪犯人體，熱勝消耗津液",
        "C": "陰勝則熱，陰勝則陽病",
        "D": "寒邪直中太陰，出現寒證，同時耗散陽氣"
      }
    },
    {
      "id": 12,
      "question": "《素問．生氣通天論篇》認為人若不能服天氣而通神明，則會臟腑氣血失調，衛氣不固而腠理疏鬆， 下列敘述何者正確？",
      "options": {
        "A": "此謂外感，氣之削也",
        "B": "此謂陰傷，血之削也",
        "C": "此謂自傷，氣之削也",
        "D": "此謂內傷，血之削也"
      }
    },
    {
      "id": 13,
      "question": "根據《素問．陰陽應象大論篇》，情志的調和與養生有極大的關係，而五志中的「怒」會傷下列何臟？",
      "options": {
        "A": "脾",
        "B": "肺",
        "C": "腎",
        "D": "肝"
      }
    },
    {
      "id": 14,
      "question": "根據《素問．上古天真論篇》，有關女子35 歲時的生理變化，下列敘述何者正確？",
      "options": {
        "A": "任脈虛，太衝脈衰少",
        "B": "面始焦，髮始墮",
        "C": "筋骨堅，髮長極",
        "D": "真牙生而長極"
      }
    },
    {
      "id": 15,
      "question": "根據《素問．陰陽應象大論篇》，過食鹹味食物可造成下列何者損傷？",
      "options": {
        "A": "筋",
        "B": "皮",
        "C": "血",
        "D": "肉"
      }
    },
    {
      "id": 16,
      "question": "根據《素問．陰陽應象大論篇》，食物味薄者的陰陽屬性為下列何者？",
      "options": {
        "A": "陽中之陽",
        "B": "陽中之陰",
        "C": "陰中之陽",
        "D": "陰中之陰"
      }
    },
    {
      "id": 17,
      "question": "有關「血虛生風證」之敘述，下列何者最正確？",
      "options": {
        "A": "血不榮絡，筋脈失養",
        "B": "多由肝腎陰耗傷引起",
        "C": "臨床常見神昏、譫語",
        "D": "肝陽升動無制"
      }
    },
    {
      "id": 18,
      "question": "下列奇恆之腑中，與腎最無關係者為何？",
      "options": {
        "A": "脈",
        "B": "腦",
        "C": "骨、髓",
        "D": "女子胞"
      }
    },
    {
      "id": 19,
      "question": "有關《難經》腎間動氣之理論，下列敘述何者錯誤？",
      "options": {
        "A": "又名原氣",
        "B": "生理上，在內經中稱為壯火",
        "C": "原氣由十二經絡五腧穴之俞穴注入經絡中",
        "D": "留止於十二經絡之原穴"
      }
    },
    {
      "id": 20,
      "question": "《難經》中稱「四時旺脈」，以下列何氣為本？",
      "options": {
        "A": "衛氣",
        "B": "營氣",
        "C": "胃氣",
        "D": "宗氣"
      }
    },
    {
      "id": 21,
      "question": "有關臟腑之募俞穴，下列敘述何者錯誤？",
      "options": {
        "A": "俞穴為臟腑氣輸轉至背部之處",
        "B": "募穴為臟腑氣結聚之處",
        "C": "募穴在陰，指穴位在胸腹部",
        "D": "募穴聚集其臟腑同名經絡之經氣"
      }
    },
    {
      "id": 22,
      "question": "有關營氣的概念，下列敘述何者錯誤？",
      "options": {
        "A": "營氣者，泌其津液，注之於脈，化以為血，以榮四末，內注五臟六腑",
        "B": "氣從太陰出，注手陽明，上行注足陽明",
        "C": "行於脈外之氣，晝夜營周不休",
        "D": "富於營養，故又稱榮氣"
      }
    },
    {
      "id": 23,
      "question": "下列何者不是用來評估「腎」藏象生理活動的特點？",
      "options": {
        "A": "生育功能是否正常",
        "B": "消化功能是否正常",
        "C": "小便是否正常",
        "D": "骨骼硬度或骨質是否充足"
      }
    },
    {
      "id": 24,
      "question": "根據中醫藏象理論，有關肝的特性，下列敘述何者錯誤？",
      "options": {
        "A": "肝主升發",
        "B": "肝喜條達",
        "C": "肝體陰而用陽",
        "D": "其志為思"
      }
    },
    {
      "id": 25,
      "question": "《內經》中有關「氣口」、「魄門」的敘述，下列何者正確？",
      "options": {
        "A": "魄門為五臟之主",
        "B": "氣口為五臟之使",
        "C": "五臟六腑之氣味，變見於魄門",
        "D": "氣口亦太陰也"
      }
    },
    {
      "id": 26,
      "question": "根據《內經》的中醫藏象學說，有關魂魄之敘述，下列何者正確？",
      "options": {
        "A": "魂生於腎，腎藏精，因此《內經》認為魂是一種並精出入的氣",
        "B": "肝藏魂，所以魂執行思考、決策等功能的主要處所是在肝",
        "C": "魂能夠協助執行心主神明的功能",
        "D": "魂魄二者有陰陽的相對關係，睡眠時魂歸於肝，因此魂屬陰、魄屬陽"
      }
    },
    {
      "id": 27,
      "question": "根據《難經》所述「太陽之至，洪大而長」是指下列何種脈象？",
      "options": {
        "A": "平脈",
        "B": "是《傷寒論》中太陽病之主脈",
        "C": "太陽膀胱經之病脈",
        "D": "是《傷寒論》中太陽病之死脈"
      }
    },
    {
      "id": 28,
      "question": "有關元氣的敘述，下列何者最正確？",
      "options": {
        "A": "父母之精是元氣的唯一來源",
        "B": "人死亡後，元氣就會散失",
        "C": "元氣只存在三焦，不存在經絡中",
        "D": "經脈氣循行中斷，生命即會死亡"
      }
    },
    {
      "id": 29,
      "question": "「泌糟粕，蒸津液，化其精微」，是下列何臟腑部位的生理功能敘述？",
      "options": {
        "A": "上焦",
        "B": "中焦",
        "C": "下焦",
        "D": "胞絡"
      }
    },
    {
      "id": 30,
      "question": "根據《靈樞．通天篇》對於「陽人、陰人」之敘述，「見人有亡，常若所得；……見人有榮，乃反 慍怒……。」是下列何種人之特徵？",
      "options": {
        "A": "太陰之人",
        "B": "少陰之人",
        "C": "太陽之人",
        "D": "少陽之人"
      }
    },
    {
      "id": 31,
      "question": "承上題，此類人外表形態之特徵為何？",
      "options": {
        "A": "其狀清然竊然，……立而躁嶮，行而似伏",
        "B": "其狀立而好仰，行則好搖",
        "C": "其狀軒軒儲儲，反身折膕",
        "D": "其狀黮黮然黑色，念然下意"
      }
    },
    {
      "id": 32,
      "question": "有關現代醫學解剖所稱之「腓腸」，其相應之中醫解剖名詞為下列何者？",
      "options": {
        "A": "膕",
        "B": "腨",
        "C": "股",
        "D": "脛"
      }
    },
    {
      "id": 33,
      "question": "中醫解剖名詞「大椎」，位於下列現代醫學解剖之何處？",
      "options": {
        "A": "第六頸椎",
        "B": "第七頸椎",
        "C": "第一胸椎",
        "D": "第二胸椎"
      }
    },
    {
      "id": 34,
      "question": "根據《靈樞．經脈篇》所記載，大包是十五別絡中何脈之名稱？",
      "options": {
        "A": "足太陰之別",
        "B": "足少陰之別",
        "C": "脾之大絡",
        "D": "督脈之別"
      }
    },
    {
      "id": 35,
      "question": "大雄近兩週熬夜準備考試，出現顴紅、咽乾、耳下兩頷腫痛感，還有內側眼角抽動的情況。下列那 一條經絡與上述病症最有關係？",
      "options": {
        "A": "手少陽三焦經",
        "B": "手太陽小腸經",
        "C": "足少陽膽經",
        "D": "足陽明胃經"
      }
    },
    {
      "id": 36,
      "question": "根據《難經》，子宮腫瘤與下列何經絡疾病最有關係？",
      "options": {
        "A": "任脈",
        "B": "督脈",
        "C": "陰蹻脈",
        "D": "帶脈"
      }
    },
    {
      "id": 37,
      "question": "臨床上腦、脊髓與腎方面相關的疾病，若要以奇經八脈考量來治療，應選擇下列何者？",
      "options": {
        "A": "任脈",
        "B": "督脈",
        "C": "帶脈",
        "D": "衝脈"
      }
    },
    {
      "id": 38,
      "question": "根據《素問．靈蘭秘典論篇》對藏象之論述，下列何者正確？",
      "options": {
        "A": "膽者，將軍之官",
        "B": "三焦者，州都之官",
        "C": "小腸者，受盛之官",
        "D": "膻中者，中正之官"
      }
    },
    {
      "id": 39,
      "question": "根據《靈樞．海論篇》的敘述，「內屬於臟腑，外絡於肢節」為下列何者？",
      "options": {
        "A": "十二經脈",
        "B": "十二經別",
        "C": "十五絡脈",
        "D": "十二經筋"
      }
    },
    {
      "id": 40,
      "question": "《靈樞．經脈篇》記載經脈的循行，「起於大指叢毛之際」的是：",
      "options": {
        "A": "肝經",
        "B": "脾經",
        "C": "腎經",
        "D": "大腸經"
      }
    },
    {
      "id": 41,
      "question": "林先生出現咽乾、胸悶、嘔逆、腹瀉、小便不利等症狀。下列那一條經絡與其相關的臟腑與上述病 症最有關係？",
      "options": {
        "A": "足陽明胃經",
        "B": "足太陽膀胱經",
        "C": "足厥陰肝經",
        "D": "足太陰脾經"
      }
    },
    {
      "id": 42,
      "question": "根據《素問．平人氣象論篇》所記載，下列有關胃之大絡的敘述何者正確？",
      "options": {
        "A": "名曰建里",
        "B": "出於缺盆下",
        "C": "貫鬲絡肺",
        "D": "脈營氣"
      }
    },
    {
      "id": 43,
      "question": "根據《素問．上古天真論篇》論述，理想中的上古長壽之人，皆遵循下列何者之道？",
      "options": {
        "A": "陰陽",
        "B": "御神",
        "C": "快心",
        "D": "生樂"
      }
    },
    {
      "id": 44,
      "question": "根據《靈樞．經脈篇》論述，「鼽衄」非下列何經之病候？",
      "options": {
        "A": "大腸手陽明之脈",
        "B": "胃足陽明之脈",
        "C": "膀胱足太陽之脈",
        "D": "小腸手太陽之脈"
      }
    },
    {
      "id": 45,
      "question": "根據《靈樞．經脈篇》，有關心經循行與相關病候的敘述，下列何者正確？",
      "options": {
        "A": "起於心中，出屬於心，下膈，絡小腸",
        "B": "其直者，復從心系橫出肺，下出腋下，下循臑內後廉，行太陰心主之後",
        "C": "是動則病嗌乾，心痛，渴而欲飲，是為臂厥",
        "D": "是主心所生病者，目黃，脇痛，臑臂外後廉痛厥，掌中熱痛"
      }
    },
    {
      "id": 46,
      "question": "根據《靈樞．經脈篇》，有關肝經循行與相關病候之敘述，下列何者正確？",
      "options": {
        "A": "起於大指叢毛之際，上循足跗上廉，去內踝二寸，上踝五寸，交出太陰之後",
        "B": "上貫膈，布脇肋，循喉嚨之後，上入頏顙，連目系，上出額，與足太陽會於巔",
        "C": "其支者，從目內眥，下頰裏，環唇內",
        "D": "是主肝所生病者，胸滿，嘔逆，飧泄，狐疝，遺溺，閉癃"
      }
    },
    {
      "id": 47,
      "question": "根據《靈樞．經筋篇》論述，下列何經脈之經筋分布未至陰器？",
      "options": {
        "A": "足少陽之筋",
        "B": "足陽明之筋",
        "C": "足少陰之筋",
        "D": "足太陰之筋"
      }
    },
    {
      "id": 48,
      "question": "有關十二經脈於身體的走向與分布，下列敘述何者正確？",
      "options": {
        "A": "足三陰經均不上頭，繫頸而還",
        "B": "足少陰腎經位於前側體腔，走在足陽明胃經之內側",
        "C": "手少陽三焦經自頸後上頰，至目銳眥，卻入耳中",
        "D": "手少陰心經有支脈行頭面之深部"
      }
    },
    {
      "id": 49,
      "question": "外感傷寒病的病程發展，如果出現頭痛連巔頂、欲嘔吐的徵象，可能與身體之那一條經絡及其連屬 的臟腑最有關係？",
      "options": {
        "A": "足少陰腎經",
        "B": "足厥陰肝經",
        "C": "足少陽膽經",
        "D": "足陽明胃經"
      }
    },
    {
      "id": 50,
      "question": "下列何者最不可能為「陰盛生內寒」的誘發因素？",
      "options": {
        "A": "血脈凝泣",
        "B": "寒積胸中",
        "C": "厥氣上逆",
        "D": "肝鬱氣滯"
      }
    },
    {
      "id": 51,
      "question": "下列何者為風邪一般侵犯人體之途徑？",
      "options": {
        "A": "臟→經絡→孫絡→皮毛→腑",
        "B": "皮毛→臟→經絡→孫絡→腑",
        "C": "皮毛→孫絡→經絡→腑→臟",
        "D": "孫絡→皮毛→經絡→腑→臟"
      }
    },
    {
      "id": 52,
      "question": "「首如裹」為病人外感於下列何種病邪？",
      "options": {
        "A": "風",
        "B": "濕",
        "C": "寒",
        "D": "暑"
      }
    },
    {
      "id": 53,
      "question": "有關環境致病因素「六淫」的敘述，下列何者錯誤？",
      "options": {
        "A": "風為陽邪，其性開泄，易襲陽位",
        "B": "寒為陰邪，易傷陽氣",
        "C": "濕為百病之長，易挾五邪",
        "D": "燥性乾澀，易傷津液"
      }
    },
    {
      "id": 54,
      "question": "根據《素問．至真要大論篇》對治療法則之論述，下列何者屬「從治法」？",
      "options": {
        "A": "寒因寒用",
        "B": "寒者熱之",
        "C": "熱者寒之",
        "D": "急者緩之"
      }
    },
    {
      "id": 55,
      "question": "有關七情致病對臟腑產生之影響，下列敘述何者正確？",
      "options": {
        "A": "怒傷心",
        "B": "驚傷脾",
        "C": "喜傷肺",
        "D": "恐傷腎"
      }
    },
    {
      "id": 56,
      "question": "下列何者為「大厥」之病機？",
      "options": {
        "A": "血并於上，氣并於下",
        "B": "血并於下，氣并於上",
        "C": "血之與氣，并走於上",
        "D": "血之與氣，并走於下"
      }
    },
    {
      "id": 57,
      "question": "下列病機之敘述，何者較少導致肺氣宣肅失常？",
      "options": {
        "A": "痰濁上犯，內阻肺絡",
        "B": "肝升太過，氣火上逆",
        "C": "脾陰不足，燥熱內生",
        "D": "腎陽虛衰，水氣凌心"
      }
    },
    {
      "id": 58,
      "question": "根據《素問．陰陽應象大論篇》記載：「陰陽者，天地之道也，萬物之綱紀，變化之父母，生殺之 本始，神明之府也……。」有關清氣與濁氣對人體的影響，下列敘述何者正確？",
      "options": {
        "A": "清氣在下，則生飱瀉；濁氣在上，則生䐜脹",
        "B": "清氣在上，則生飱瀉；濁氣在下，則生䐜脹",
        "C": "清氣在下，則生䐜脹；濁氣在上，則生飱瀉",
        "D": "清氣在上，則生䐜脹；濁氣在下，則生飱瀉"
      }
    },
    {
      "id": 59,
      "question": "有關津液大量流失，導致的病機狀態，下列敘述何者最不適宜？",
      "options": {
        "A": "由於津液大量流失，氣失其依附隨津液外泄，而導致陽氣暴脫",
        "B": "由於津液虧耗，血脈中的津液乾涸，從而導致血燥",
        "C": "由於津液虧耗，血虛導致血行不暢而生血瘀",
        "D": "由於津液虧耗，影響氣化失常，而導致水停氣阻"
      }
    },
    {
      "id": 60,
      "question": "根據《素問．至真要大論篇》對「病機十九條」之論述，下列何者屬「肺」的病機？",
      "options": {
        "A": "諸熱瞀瘛",
        "B": "諸氣膹鬱",
        "C": "諸病有聲，鼓之如鼓",
        "D": "諸逆衝上"
      }
    },
    {
      "id": 61,
      "question": "根據《素問．熱論篇》對「傷寒……二日，陽明受之」表現症狀之敘述，下列何者正確？",
      "options": {
        "A": "腰脊強",
        "B": "目痛而鼻乾",
        "C": "頭項痛",
        "D": "耳聾"
      }
    },
    {
      "id": 62,
      "question": "有關《內經》對不同部位血絡特性之論述，下列何者錯誤？",
      "options": {
        "A": "陽絡傷則血外溢，血外溢則前血",
        "B": "陰絡傷則血內溢，血內溢則後血",
        "C": "陰絡之色應其經",
        "D": "陽絡之色變無常，隨四時而行也"
      }
    },
    {
      "id": 63,
      "question": "簡先生在電廠工作，逐漸出現身熱、汗出、口渴、便秘，下列病因何者最可能？",
      "options": {
        "A": "熱",
        "B": "風",
        "C": "寒",
        "D": "濕"
      }
    },
    {
      "id": 64,
      "question": "下列何種情志異常是造成《素問．生氣通天論篇》所論「薄厥」的主要病機？",
      "options": {
        "A": "大喜",
        "B": "大怒",
        "C": "大悲",
        "D": "大恐"
      }
    },
    {
      "id": 65,
      "question": "28 歲女性患者，一喝冷飲即誘發咳嗽。有關其致病病機之論述，下列何者最正確？",
      "options": {
        "A": "其寒飲食入胃，從胃絡屬脾，脾脈上注於心",
        "B": "其寒飲食入胃，從胃上貫膈入肺則肺寒",
        "C": "其寒飲食入胃，復從肝脈上注肺",
        "D": "其寒飲食入胃，從肺脈上至於肺則肺寒"
      }
    },
    {
      "id": 66,
      "question": "《內經》有關時間醫學之敘述，下列何者錯誤？",
      "options": {
        "A": "《素問．金匱真言論篇》：合夜至雞鳴，天之陰，陰中之陽也",
        "B": "《靈樞．營衛生會篇》：平旦，陰盡而陽受氣矣",
        "C": "《靈樞．口問篇》：衛氣晝日行於陽，夜半則行於陰",
        "D": "《素問．生氣通天論篇》：平旦人氣生，日中而陽氣隆"
      }
    },
    {
      "id": 67,
      "question": "小華外出淋雨後，出現發燒38℃、頭痛、項痛、目痛、鼻乾，下列敘述何者正確？",
      "options": {
        "A": "可能會有腰脊僵硬不適的症狀",
        "B": "熱邪客於太陽與陽明經",
        "C": "屬兩感於寒",
        "D": "宜汗下同治"
      }
    },
    {
      "id": 68,
      "question": "有關氣血功能失調導致的病變，下列敘述何者錯誤？",
      "options": {
        "A": "氣不足則固攝血液功能減退，而致血不循經，溢出脈外，導致氣不攝血之出血病態",
        "B": "血為氣之載體，血脫則氣失其附載，故氣亦隨之暴脫而亡失",
        "C": "可因氣虛，血無以生化而日漸虧少，從而形成氣血兩虛病證",
        "D": "氣血失調，影響為臟腑經絡失去濡養，但筋肉肌膚不受其影響"
      }
    },
    {
      "id": 69,
      "question": "根據《素問．奇病論篇》中「膽虛，氣上溢」，其病口之五味為下列何者？",
      "options": {
        "A": "口苦",
        "B": "口甘",
        "C": "口酸",
        "D": "口鹹"
      }
    },
    {
      "id": 70,
      "question": "王先生近一個月經常熬夜工作，近日出現悶悶不樂，頭重痛，雙眼上視且目赤等症狀，最可能即將 發作下列何種疾病？",
      "options": {
        "A": "癲疾",
        "B": "腦逆",
        "C": "腦爍",
        "D": "首風"
      }
    },
    {
      "id": 71,
      "question": "有關「腎氣不固證」之敘述，下列何者最不適宜？",
      "options": {
        "A": "腎氣不固是指腎的封藏功能減退",
        "B": "易導致腎中精氣流失",
        "C": "二便失於固攝",
        "D": "易導致水腫"
      }
    },
    {
      "id": 72,
      "question": "根據《素問．痿論篇》有關痿症之論述，下列何者正確？",
      "options": {
        "A": "五臟皆因肺熱葉焦，發為痿症",
        "B": "治痿獨取太陰",
        "C": "悲哀太盛，則胞絡絕而陽氣內動而數溲血，發則為筋痿",
        "D": "入房太甚，宗筋弛縱，發為骨痿"
      }
    },
    {
      "id": 73,
      "question": "根據《素問．痹論篇》有關「痹症」之病機論述，下列何者正確？",
      "options": {
        "A": "其留連筋骨間者易已",
        "B": "其入臟者之病情較入腑者為嚴重",
        "C": "其留於皮膚間者疼久",
        "D": "其入腑者由六經合穴而入"
      }
    },
    {
      "id": 74,
      "question": "根據《靈樞．水脹篇》，有關「膚脹」之病理變化，下列敘述何者錯誤？",
      "options": {
        "A": "火氣客於皮膚之間",
        "B": "腹大身盡腫",
        "C": "按其腹，窅而不起",
        "D": "腹色不變"
      }
    },
    {
      "id": 75,
      "question": "根據《素問．舉痛論篇》，脇肋與少腹相引痛者，為寒氣客於下列何處所致？",
      "options": {
        "A": "小腸膜原之間",
        "B": "厥陰之脈",
        "C": "陰股",
        "D": "腸胃"
      }
    },
    {
      "id": 76,
      "question": "根據《素問．痹論篇》有關「痹客於五臟六腑」之論述，下列何者正確？",
      "options": {
        "A": "腎痹者，夜臥則驚，多飲，數小便",
        "B": "脾痹者，善脹，尻以代踵，脊以代頭",
        "C": "肺痹者，暴上氣而喘，上為清涕，厥氣上則悲",
        "D": "心痹者，脈不通，煩則心下鼓，厥氣上則恐"
      }
    },
    {
      "id": 77,
      "question": "根據《素問．厥論篇》有關六經之厥的症狀論述，下列何者正確？",
      "options": {
        "A": "巨陽之厥，則腫首頭重，足不能行，發為眴仆",
        "B": "陽明之厥，則腹滿䐜脹，不欲食，食則嘔",
        "C": "厥陰之厥，則癲疾欲走，腹滿不得臥，面赤而熱",
        "D": "少陰之厥，則口乾溺赤，涇溲不利，好臥屈膝"
      }
    },
    {
      "id": 78,
      "question": "根據《素問．奇病論篇》提出癃病患者「五有餘」與「二不足」之臨床表現，下列何者為「不足」 之表現？",
      "options": {
        "A": "一日數十溲",
        "B": "喘息氣逆",
        "C": "身熱如炭",
        "D": "頸膺如格"
      }
    },
    {
      "id": 79,
      "question": "患者旅居瑞士，嗜食起司鍋及巧克力，後來漸漸感到嘴巴中一直有甜甜的感覺，下列相關敘述何者 錯誤？",
      "options": {
        "A": "此名為「脾癉」，可治之以酸",
        "B": "津液在脾，故令人口甘",
        "C": "此因數食甘美而多肥者所致",
        "D": "此因飲食引起中滿、內熱，可轉為消渴"
      }
    },
    {
      "id": 80,
      "question": "根據《素問．痹論篇》生理病理的敘述，下列何者錯誤？",
      "options": {
        "A": "營衛協行，不與風寒濕三氣合，故不為痹",
        "B": "營者，水穀之精氣，循脈上下，貫五藏絡六府也",
        "C": "衛者，水穀之悍氣也，其氣慓疾滑利，能入於脈中也",
        "D": "衛氣循于皮膚之中，以及分肉之間，熏於肓膜，散於胸腹"
      }
    }
  ]
}
